software_manager/Configuration.py
software_manager/Menu.py
software_manager/Utils.py
software_manager/__init__.py
software_manager-0.9.0.dist-info/METADATA
software_manager-0.9.0.dist-info/WHEEL
software_manager-0.9.0.dist-info/top_level.txt
software_manager-0.9.0.dist-info/RECORD
