Metadata-Version: 2.1
Name: software-manager
Version: 0.9.0
Summary: Software manager useful for installing programs
Author: C-JeanDev Jean Claude Coppola
Author-email: <jeanclaudecoppola83@gmail.com>
Keywords: python,software,software_manager,manager,install,
Classifier: Development Status :: 1 - Planning
Classifier: Intended Audience :: Developers
Classifier: Programming Language :: Python :: 3
Classifier: Operating System :: Unix
Classifier: Operating System :: MacOS :: MacOS X
Classifier: Operating System :: Microsoft :: Windows
Requires-Dist: getch
Requires-Dist: print-color
